pyH2oMojo/__init__.py
pyH2oMojo/pyH2oMojo-1.0.jar
pyH2oMojo-0.1.1.dist-info/METADATA
pyH2oMojo-0.1.1.dist-info/RECORD
pyH2oMojo-0.1.1.dist-info/WHEEL
pyH2oMojo-0.1.1.dist-info/top_level.txt
