Metadata-Version: 2.1
Name: pyH2oMojo
Version: 0.1.1
Summary: H2O MOJO wrapper - allows predictions from python without the webserver overhead.
Home-page: https://github.com/blakebjorn/pyH2oMojo
Author: Blake Anderson
Author-email: blakebanders@gmail.com
License: UNKNOWN
Platform: UNKNOWN
Classifier: Programming Language :: Python :: 3
Classifier: License :: OSI Approved :: MIT License
Classifier: Operating System :: OS Independent
